jamcodec/__init__.py
jamcodec/base.py
jamcodec/constants.py
jamcodec/exceptions.py
jamcodec/mixins.py
jamcodec/types.py
jamcodec-0.1.4.dist-info/licenses/LICENSE
jamcodec-0.1.4.dist-info/METADATA
jamcodec-0.1.4.dist-info/WHEEL
jamcodec-0.1.4.dist-info/top_level.txt
jamcodec-0.1.4.dist-info/RECORD
