Metadata-Version: 2.4
Name: jamcodec
Version: 0.1.4
Summary: Python JAM Codec Library
Author-email: JAMdot Technologies <dev@jamdot.tech>
Project-URL: Homepage, https://github.com/JAMdotTech/py-jam-codec
Keywords: jam,codec
Classifier: Development Status :: 5 - Production/Stable
Classifier: Intended Audience :: Developers
Classifier: License :: OSI Approved :: Apache Software License
Classifier: Programming Language :: Python :: 3
Requires-Python: <4,>=3.8
License-File: LICENSE
Requires-Dist: more-itertools>=8.6.0
Provides-Extra: dev
Requires-Dist: coverage==5.3; extra == "dev"
Requires-Dist: pytest>=6.1.2; extra == "dev"
Requires-Dist: mkdocs; extra == "dev"
Requires-Dist: mkdocs-material; extra == "dev"
Requires-Dist: mkdocs-autorefs; extra == "dev"
Requires-Dist: mkdocstrings; extra == "dev"
Requires-Dist: mkdocstrings[python]; extra == "dev"
Dynamic: license-file
